sentiebl/__init__.py
sentiebl/config.py
sentiebl/dictionary.py
sentiebl/main.py
sentiebl-0.1.1.dist-info/METADATA
sentiebl-0.1.1.dist-info/WHEEL
sentiebl-0.1.1.dist-info/top_level.txt
sentiebl-0.1.1.dist-info/RECORD
