Metadata-Version: 2.1
Name: sentiebl
Version: 0.1.1
Summary: Systematic Elicitation of Non-Trivial and Insecure Emergent Behaviors in LLMs
Home-page: https://github.com/mmfarabi/sentiebl
Author: Mirza Milan Farabi
Author-email: mmfarabi28m@gmail.com
License: UNKNOWN
Keywords: llm,gpt-oss,red-teaming,openai,ollama,ai-safety,vulnerability-analysis,prompt-injection,ai-security,sentiebl,llm-testing,llm-auditor
Platform: UNKNOWN
Classifier: Development Status :: 5 - Production/Stable
Classifier: Intended Audience :: Developers
Classifier: Intended Audience :: Science/Research
Classifier: License :: OSI Approved :: Apache Software License
Classifier: Programming Language :: Python :: 3
Classifier: Programming Language :: Python :: 3.8
Classifier: Programming Language :: Python :: 3.9
Classifier: Programming Language :: Python :: 3.10
Classifier: Topic :: Security
Classifier: Topic :: Scientific/Engineering :: Artificial Intelligence
Classifier: Topic :: Software Development :: Testing
Requires-Python: >=3.8
Requires-Dist: ipython
Requires-Dist: matplotlib
Requires-Dist: ollama
Requires-Dist: openai
Requires-Dist: pandas
